tachymeter/__init__.py
tachymeter/tachyon.py
tachymeter/util.py
tachymeter-0.1.0.dist-info/LICENSE
tachymeter-0.1.0.dist-info/METADATA
tachymeter-0.1.0.dist-info/WHEEL
tachymeter-0.1.0.dist-info/top_level.txt
tachymeter-0.1.0.dist-info/RECORD
